CaGeo/__init__.py
CaGeo/algorithms/AggregateFeatures.py
CaGeo/algorithms/BasicFeatures.py
CaGeo/algorithms/SegmentFeatures.py
CaGeo/algorithms/__init__.py
CaGeo/algorithms/utils.py
CaGeo/classes/__init__.py
CaGeo-0.0.4.post1.dist-info/LICENSE
CaGeo-0.0.4.post1.dist-info/METADATA
CaGeo-0.0.4.post1.dist-info/WHEEL
CaGeo-0.0.4.post1.dist-info/top_level.txt
CaGeo-0.0.4.post1.dist-info/RECORD
