Metadata-Version: 2.1
Name: CaGeo
Version: 0.0.4.post1
Summary: Package description
Home-page: https://github.com/USERNAME/project
Author: Cristiano Landi
Author-email: cri98li@gmail.com
License: BSD-Clause-2
Keywords: keyword1 keyword2 keyword3
Classifier: Development Status :: 3 - Alpha
Classifier: Intended Audience :: Developers
Classifier: Topic :: Software Development :: Build Tools
Classifier: License :: OSI Approved :: BSD License
Classifier: Operating System :: POSIX :: Other
Classifier: Operating System :: MacOS
Classifier: Programming Language :: Python
Classifier: Programming Language :: Python :: 3
License-File: LICENSE
Requires-Dist: geopy
Requires-Dist: numpy
Requires-Dist: scipy
Provides-Extra: flag
